{
  "id": "syn_0175",
  "project_name": "Shopping Mall at Outer Ring Road",
  "category": "finishes",
  "text": "The scope of work includes paint, tile, cement plaster for the Shopping Mall at Outer Ring Road project located at roof level. The contractor shall supply all materials and execute the works as per the specifications given below.\n\nBILL OF QUANTITIES\n\nS.No  Description  Qty  Unit  Rate  Amount\n1  Fabricate and erect DB  86  nos  2381  25382\n2  Provide and lay Class 2 POP  95  sqm  527  76053\n3  Lay Fe500 MS plate 20mm thick  250  ltr  1700  79988\n4  Fix brickbat coba 12mm thick  61  nos  1116  61625\n5  Supply and fix MS door  283  rmt  2766  23517\n6  Lay HDPE pipe 12mm thick  268  cum  3942  21435\n\nTECHNICAL SPECIFICATIONS\n\n1. MATERIALS\n   All materials shall be of best quality conforming to relevant Indian Standards.\n   The contractor shall submit samples of all materials for approval before use.\n\n2. WORKMANSHIP\n   All works shall be carried out as per IS codes and good construction practice.\n   The engineer-in-charge shall have the right to reject any defective material or workmanship.\n\n3. TESTING\n   All materials shall be tested as per relevant IS codes.\n   Test certificates from NABL accredited labs shall be submitted.\n\n\nGENERAL TERMS AND CONDITIONS\n\n1. Payment: 80% advance on materials at site, balance within 15 days of completion.\n2. Completion: Within 60 days from date of work order.\n3. Validity: Quotation valid for 90 days from submission date.\n4. Warranty: Defects arising within 12 months from completion shall be rectified free of cost.\n5. Taxes: GST extra as applicable.\n",
  "text_for_ner": "The scope of work includes paint, tile, cement plaster for the Shopping Mall at Outer Ring Road project located at roof level. The contractor shall supply all materials and execute the works as per the specifications given below. Fabricate and erect DB Provide and lay Class 2 POP Lay Fe500 MS plate 20mm thick Fix brickbat coba 12mm thick Supply and fix MS door Lay HDPE pipe 12mm thick",
  "sections": {
    "scope": "The scope of work includes paint, tile, cement plaster for the Shopping Mall at Outer Ring Road project located at roof level. The contractor shall supply all materials and execute the works as per the specifications given below.",
    "boq_table": [
      [
        "S.No",
        "Description",
        "Qty",
        "Unit",
        "Rate",
        "Amount"
      ],
      [
        "1",
        "Fabricate and erect DB",
        "86",
        "nos",
        "2381",
        "25382"
      ],
      [
        "2",
        "Provide and lay Class 2 POP",
        "95",
        "sqm",
        "527",
        "76053"
      ],
      [
        "3",
        "Lay Fe500 MS plate 20mm thick",
        "250",
        "ltr",
        "1700",
        "79988"
      ],
      [
        "4",
        "Fix brickbat coba 12mm thick",
        "61",
        "nos",
        "1116",
        "61625"
      ],
      [
        "5",
        "Supply and fix MS door",
        "283",
        "rmt",
        "2766",
        "23517"
      ],
      [
        "6",
        "Lay HDPE pipe 12mm thick",
        "268",
        "cum",
        "3942",
        "21435"
      ]
    ],
    "specifications": "TECHNICAL SPECIFICATIONS\n\n1. MATERIALS\n   All materials shall be of best quality conforming to relevant Indian Standards.\n   The contractor shall submit samples of all materials for approval before use.\n\n2. WORKMANSHIP\n   All works shall be carried out as per IS codes and good construction practice.\n   The engineer-in-charge shall have the right to reject any defective material or workmanship.\n\n3. TESTING\n   All materials shall be tested as per relevant IS codes.\n   Test certificates from NABL accredited labs shall be submitted.\n",
    "terms": "GENERAL TERMS AND CONDITIONS\n\n1. Payment: 80% advance on materials at site, balance within 15 days of completion.\n2. Completion: Within 60 days from date of work order.\n3. Validity: Quotation valid for 90 days from submission date.\n4. Warranty: Defects arising within 12 months from completion shall be rectified free of cost.\n5. Taxes: GST extra as applicable.\n"
  },
  "metadata": {
    "boq_ground_truth": [
      {
        "item_no": 1,
        "action": "Fabricate and erect",
        "material": "DB",
        "grade": "",
        "dimension": "",
        "quantity": 86,
        "unit": "no.",
        "standard": [
          "IS 9537"
        ]
      },
      {
        "item_no": 2,
        "action": "Provide and lay",
        "material": "POP",
        "grade": "Class 2",
        "dimension": "",
        "quantity": 95,
        "unit": "m^2",
        "standard": [
          "IS 1661"
        ]
      },
      {
        "item_no": 3,
        "action": "Lay",
        "material": "MS plate",
        "grade": "Fe500",
        "dimension": "20mm thick",
        "quantity": 250,
        "unit": "ltr",
        "standard": [
          "IS 2062"
        ]
      },
      {
        "item_no": 4,
        "action": "Fix",
        "material": "brickbat coba",
        "grade": "",
        "dimension": "12mm thick",
        "quantity": 61,
        "unit": "no.",
        "standard": [
          "IS 1582"
        ]
      },
      {
        "item_no": 5,
        "action": "Supply and fix",
        "material": "MS door",
        "grade": "",
        "dimension": "",
        "quantity": 283,
        "unit": "rmt",
        "standard": [
          "IS 456"
        ]
      },
      {
        "item_no": 6,
        "action": "Lay",
        "material": "HDPE pipe",
        "grade": "",
        "dimension": "12mm thick",
        "quantity": 268,
        "unit": "m^3",
        "standard": [
          "IS 1239"
        ]
      }
    ],
    "num_items": 6
  }
}